[
  {
    "name": "مرکز تحقیقاتی APT IRAN",
    "link": "https://t.me/APTIRAN",
    "status": "Active",
    "tags": [
      "red",
      "threat-intel",
      "blue",
      "osint",
      "incident-response"
    ],
    "description": ""
  },
  {
    "name": "CTF Challenges",
    "link": "https://t.me/ctf_challenges",
    "status": "Unknown",
    "tags": [
      "ctf",
      "challenges",
      "education"
    ],
    "description": ""
  },
  {
    "name": "امنیت سایبری",
    "link": "https://t.me/cybersecurity_fa",
    "status": "Active",
    "tags": [
      "blue",
      "persian",
      "education"
    ],
    "description": "لورم ایپسوم متن ساختگی با تولید سادگی نامفهوم از صنعت چاپhttps://emojipedia.org/flag-iran لورم ایپسوم متن ساختگی با تولید سادگی نامفهوم از صنعت چاپ"
  },
  {
    "name": "CyberSecurity News",
    "link": "https://t.me/CyberSecurityNews",
    "status": "Active",
    "tags": [
      "news",
      "blue",
      "persian",
      "red",
      "tools",
      "exploits",
      "incident-response"
    ],
    "description": ""
  },
  {
    "name": "DFIR Community",
    "link": "https://t.me/dfir_community",
    "status": "Inactive",
    "tags": [
      "blue",
      "forensics",
      "incident-response"
    ],
    "description": ""
  },
  {
    "name": "Exploit Database",
    "link": "https://t.me/exploitdb",
    "status": "Active",
    "tags": [
      "exploits",
      "red",
      "tools"
    ],
    "description": "http://127.0.0.1:8000/"
  },
  {
    "name": "هکرنیوز",
    "link": "https://t.me/hackernews",
    "status": "Active",
    "tags": [
      "news",
      "persian",
      "academy"
    ],
    "description": "CyberSecurity News"
  },
  {
    "name": "Malware Analysis",
    "link": "https://t.me/malware_analysis",
    "status": "Active",
    "tags": [
      "malware",
      "analysis",
      "blue"
    ],
    "description": ""
  },
  {
    "name": "/var/log/ mehraz/var/log/mehraz/var/log/mehraz",
    "link": "https://t.me/mehraz_logsmehraz_logsmehraz_logs",
    "status": "Active",
    "tags": [
      "osint",
      "blue",
      "red"
    ],
    "description": "لورم ایپسوم متن ساختگی با تولید سادگی نامفهوم از صنعت چاپ لورم ایپسوم متن ساختگی با تولید سادگی نامفهوم از صنعت چاپ لورم ایپسوم متن ساختگی با تولید سادگی نامفهوم از صنعت چاپ"
  },
  {
    "name": "Web Security",
    "link": "https://t.me/websecurity",
    "status": "Active",
    "tags": [
      "web",
      "appsec",
      "blue"
    ],
    "description": ""
  }
]